Metadata-Version: 2.1
Name: xlsx2sqlite
Version: 0.4.6
Summary: Generate a Sqlite3 database from a Office Open XML file.
Home-page: https://github.com/Xgalan/xlsx2sqlite
Author: Erik Mascheri
Author-email: erik.mascheri@gmail.com
License: GPLv3
Keywords: xlsx2sqlite,sqlite3
Classifier: Development Status :: 2 - Pre-Alpha
Classifier: License :: OSI Approved :: GNU General Public License v3 (GPLv3)
Classifier: Programming Language :: Python
Classifier: Programming Language :: Python :: 3 :: Only
Classifier: Programming Language :: Python :: 3.7
Classifier: Programming Language :: Python :: 3.8
Classifier: Programming Language :: Python :: 3.9
Classifier: Programming Language :: Python :: 3.10
Classifier: Programming Language :: Python :: 3.11
Requires-Python: >=3.7
License-File: LICENSE
Requires-Dist: openpyxl (<3.1,>=3)
Requires-Dist: tablib (<=3.1.0,>=3.0.0)
Requires-Dist: Click (<8.1,>=7.1)
Requires-Dist: colorama
Requires-Dist: cached-property ; python_version < "3.8"
Provides-Extra: code_audit
Requires-Dist: black ; extra == 'code_audit'
Requires-Dist: isort ; extra == 'code_audit'
Provides-Extra: compile
Requires-Dist: wheel ; extra == 'compile'
Requires-Dist: nuitka ; extra == 'compile'
Requires-Dist: zstandard ; extra == 'compile'
Requires-Dist: build ; extra == 'compile'
Requires-Dist: twine ; extra == 'compile'
Provides-Extra: docs
Requires-Dist: Sphinx ; extra == 'docs'
Requires-Dist: sphinx-click (<3.1,>=2.7) ; extra == 'docs'
Requires-Dist: sphinx-rtd-theme (==1.0.0) ; extra == 'docs'
Provides-Extra: tests
Requires-Dist: pytest (<7,>=6) ; extra == 'tests'
Requires-Dist: coverage ; extra == 'tests'
Requires-Dist: pytest-cov ; extra == 'tests'
Requires-Dist: pytest-random-order ; extra == 'tests'
